oautom
oautom_tests
