Metadata-Version: 2.1
Name: oautom
Version: 1.0.1
Summary: UNKNOWN
Home-page: https://github.com/FabienArcellier/oautom
License: MIT
Platform: UNKNOWN
Provides-Extra: dev
